sam_subseq/IndexMap.py
sam_subseq/SamRefAlignment.py
sam_subseq/__init__.py
sam_subseq/io.py
sam_subseq/main.py
sam_subseq-0.1.0.dist-info/LICENSE
sam_subseq-0.1.0.dist-info/METADATA
sam_subseq-0.1.0.dist-info/WHEEL
sam_subseq-0.1.0.dist-info/entry_points.txt
sam_subseq-0.1.0.dist-info/top_level.txt
sam_subseq-0.1.0.dist-info/RECORD
