Metadata-Version: 2.1
Name: sam-subseq
Version: 0.1.0
Summary: Extract subsequences corresponding to annotated reference features from aligned reads in a SAM file
Author-email: Oliver Thomas <thomaso@ie-freiburg.mpg.de>
Project-URL: Repository, https://www.github.com/osthomas/sam_subseq
Classifier: Programming Language :: Python :: 3
Classifier: Operating System :: OS Independent
Requires-Python: >3.9
License-File: LICENSE
